setup.cfg
setup.py
bearform/__init__.py
bearform/errors.py
bearform/field.py
bearform/form.py
bearform/meta.py
bearform/types.py
bearform/utils.py
bearform.egg-info/PKG-INFO
bearform.egg-info/SOURCES.txt
bearform.egg-info/dependency_links.txt
bearform.egg-info/not-zip-safe
bearform.egg-info/requires.txt
bearform.egg-info/top_level.txt