Metadata-Version: 1.1
Name: bearform
Version: 1.1
Summary: Easy data conversion and validation for frontends.
Home-page: https://github.com/WiFast/bearform
Author: WiFast
Author-email: rgb@wifast.com
License: BSD-derived
Keywords: python json frontend validation
Platform: UNKNOWN
Classifier: Intended Audience :: Developers
Classifier: Programming Language :: Python
Classifier: Programming Language :: Python :: 2
Classifier: Programming Language :: Python :: 2.7
Classifier: License :: OSI Approved :: BSD License
